---
layout:     post
title:      String类
subtitle:   
date:       2018-02-11
author:     CZY
header-img: img/bg.png
catalog: true
tags:
    - Java
---

# 字符串的创建

创建一个字符串有两种方式，一种是通过构造器创建，比如：

```java
String str = new String("abc");
```

这种方式会在堆上创建一个对象，并且在常量池生成一个字符串字面量，并返回堆上的对象引用。

另一种方式是直接通过字面量对字符串进行赋值，比如：

```java
String str = "abc";
```

这种方式只会在常量池生成一个字符串字面量，返回对常量池中的字符串的引用。

这两种方式创建字符串有什么区别呢?看一下下面一段测试程序：

```java
public static void stringCreate() {
    String str1 = "a";
    String str2 = new String("a");
    String str3 = str2.intern();
    System.out.println(str1 == str2);   //结果1
    System.out.println(str1 == str3);   //结果2
}
```

结果输出为false true，结果1之前已经说明了，通过两种方式创建的字符串返回的一个是堆上的引用，一个是常量池的引用，所以两者不相等，结果为false。至于结果2，intern()方法是一个native方法，它的作用是检查常量池是否有调用者所需的字符串，如果有，返回对常量池的引用，所以结果2，str1和str3都指向常量池中的字符串，结果为true。

# 虚拟机对字符串的处理

在创建字符串的过程中，虚拟机会进行一些处理，看下面一段程序：

```java
public static void stringOpt() {
    String base = "ab";
    final String finalbase = "ab";
    String str1 = "abc";
    String str2 = "ab" + "c";
    String str3 = base + "c";
    String str4 = finalbase + "c";
    System.out.println(str1 == str2);   //结果3
    System.out.println(str1 == str3);   //结果4
    System.out.println(str1 == str4);   //结果5
}
```

运行结果分别为true false true。先看结果3，创建str2是直接用两个字面量相加的形式，对于这种情况，虚拟机会在编译期进行常量折叠，运行时str2已经指向了常量池的字面量"abc"，因此结果3为true。至于结果4，查看字节码发现：

```
        12: new           #11                 // class java/lang/StringBuilder
        15: dup
        16: invokespecial #12                 // Method java/lang/StringBuilder."<init>":()V
        19: aload_0
        20: invokevirtual #13                 // Method java/lang/StringBuilder.append:(Ljava/lang/String;)Ljava/lang/StringBuilder;
        23: ldc           #14                 // String c
        25: invokevirtual #13                 // Method java/lang/StringBuilder.append:(Ljava/lang/String;)Ljava/lang/StringBuilder;
        28: invokevirtual #15                 // Method java/lang/StringBuilder.toString:()Ljava/lang/String;
```

可以看到将1个字符串的引用和其它（字符串对象的引用或字面量）相加的情况下，虚拟机会新创建一个StringBuilder并使用append方法来完成相加的过程以提高效率，这种方式最后调用toString方法在堆上新创建一个字符串，因此结果4中str3和str1不相等。最后看结果5，结果5中其中一个String类是final型的，虚拟机会在编译期进行常量替换，因此str4经过常量折叠指向了常量池的字面量"abc"，因此结果5为true。

# intern()方法

在JDK1.7之前的版本和之后的版本对intern()方法会有些区别，主要是因为从JDK1.7开始，常量池不在永久代中，而是在堆中，方法区其他部分在JDK1.8开始就转移到元空间(metaspace)中，永久代在JDK1.8中已经完全消失。看一下下面一段测试程序：

```java
public static void internTest() {
    String str1 = new String("1") + new String("1");
    str1.intern();
    String str2 = "11";
    System.out.println(str1 == str2);   //结果6

    String str3 = "22";
    String str4 = new String("2") + new String("2");
    str4.intern();
    System.out.println(str3 == str4);   //结果7
}
```

JDK1.7及之后的运行结果为true false，之前的版本为false false。对于结果6，JDK1.7之前的版本，str1和str2本来就是一个指向不同的对象（一个在堆上，一个在常量池），所以结果为false，但对JDK1.7及之后的版本，intern()方法做了些变化，intern()方法没有在常量池中找到字符串时，按照之前的版本会在常量池新创建一个字符串，但是在1.7及之后的版本中，不会新创建字符串，而是在常量池保存一个指向堆中对象的引用，因此在下一步用字面量赋值时，返回的不是常量池的引用，而是常量池中到堆中对象的引用，所以str1和str2都指向堆中的对象，结果为true。这种方式也说明了在JDK1.7之后的版本，使用字面量赋值未必会在常量池生成一个字面量。对于结果7,先在常量池创建字面量22，之后str4调用intern就没有效果了，str3和str4分别指向常量池和堆中的字符串。

# String类hashCode方法

String类对hashCode方法进行了重写，使用的方法为BDKR算法，h=31*h+val[i],递推关系为val[0]*31^(n-1) + val[1]*31^(n-2) + ... + val[n-1]。质因子选择31，因为31容易被JVM优化，31*h=(h<<5)-i，取的太大容易溢出，取的太小分布区间太小容易冲突。
